AUTHORS
LICENSE
MANIFEST.in
README.md
setup.py
csrc/cutlass/cmake/nop.cu
csrc/cutlass/examples/00_basic_gemm/basic_gemm.cu
csrc/cutlass/examples/01_cutlass_utilities/cutlass_utilities.cu
csrc/cutlass/examples/02_dump_reg_shmem/dump_reg_shmem.cu
csrc/cutlass/examples/03_visualize_layout/options.h
csrc/cutlass/examples/03_visualize_layout/register_layout.cu
csrc/cutlass/examples/03_visualize_layout/register_layout.h
csrc/cutlass/examples/03_visualize_layout/visualize_layout.cpp
csrc/cutlass/examples/03_visualize_layout/visualize_layout.h
csrc/cutlass/examples/04_tile_iterator/tile_iterator.cu
csrc/cutlass/examples/05_batched_gemm/batched_gemm.cu
csrc/cutlass/examples/06_splitK_gemm/splitk_gemm.cu
csrc/cutlass/examples/07_volta_tensorop_gemm/volta_tensorop_gemm.cu
csrc/cutlass/examples/08_turing_tensorop_gemm/turing_tensorop_gemm.cu
csrc/cutlass/examples/09_turing_tensorop_conv2dfprop/turing_tensorop_conv2dfprop.cu
csrc/cutlass/examples/10_planar_complex/planar_complex.cu
csrc/cutlass/examples/11_planar_complex_array/planar_complex_array.cu
csrc/cutlass/examples/12_gemm_bias_relu/gemm_bias_relu.cu
csrc/cutlass/examples/13_two_tensor_op_fusion/b2b_conv2d_run.h
csrc/cutlass/examples/13_two_tensor_op_fusion/b2b_gemm_run.h
csrc/cutlass/examples/13_two_tensor_op_fusion/b2b_grouped_gemm_run.h
csrc/cutlass/examples/13_two_tensor_op_fusion/b2b_interleaved_conv2d_run.h
csrc/cutlass/examples/13_two_tensor_op_fusion/b2b_interleaved_gemm_run.h
csrc/cutlass/examples/13_two_tensor_op_fusion/fused_two_convs_f16_sm75_rf.cu
csrc/cutlass/examples/13_two_tensor_op_fusion/fused_two_convs_f16_sm75_shmem.cu
csrc/cutlass/examples/13_two_tensor_op_fusion/fused_two_convs_f16_sm80_rf.cu
csrc/cutlass/examples/13_two_tensor_op_fusion/fused_two_convs_f16_sm80_shmem.cu
csrc/cutlass/examples/13_two_tensor_op_fusion/fused_two_convs_s8_sm75_rf.cu
csrc/cutlass/examples/13_two_tensor_op_fusion/fused_two_convs_s8_sm75_shmem.cu
csrc/cutlass/examples/13_two_tensor_op_fusion/fused_two_convs_s8_sm80_rf.cu
flash_attn.egg-info/PKG-INFO
flash_attn.egg-info/SOURCES.txt
flash_attn.egg-info/dependency_links.txt
flash_attn.egg-info/requires.txt
flash_attn.egg-info/top_level.txt
