Metadata-Version: 2.1
Name: flash_attn
Version: 2.7.3
Summary: Flash Attention: Fast and Memory-Efficient Exact Attention
Home-page: https://github.com/Dao-AILab/flash-attention
Author: Tri Dao
Author-email: tri@tridao.me
Classifier: Programming Language :: Python :: 3
Classifier: License :: OSI Approved :: BSD License
Classifier: Operating System :: Unix
Requires-Python: >=3.9
License-File: LICENSE
License-File: AUTHORS
Requires-Dist: torch
Requires-Dist: einops
